pipconflictchecker/__init__.py
pipconflictchecker/checker.py
pip_conflict_checker-0.6.0.dist-info/LICENSE.md
pip_conflict_checker-0.6.0.dist-info/METADATA
pip_conflict_checker-0.6.0.dist-info/WHEEL
pip_conflict_checker-0.6.0.dist-info/entry_points.txt
pip_conflict_checker-0.6.0.dist-info/top_level.txt
pip_conflict_checker-0.6.0.dist-info/RECORD
