Metadata-Version: 1.1
Name: pip-conflict-checker
Version: 0.6.0
Summary: A tool that checks installed packages against all package requirements for version conflicts.
Home-page: https://github.com/ambitioninc/pip-conflict-checker
Author: Ambition
Author-email: opensource@ambition.com
License: MIT
Keywords: python pip dependencies conflicts versions checker
Platform: UNKNOWN
Classifier: Topic :: Utilities
Classifier: Topic :: Software Development :: Libraries :: Python Modules
Classifier: License :: OSI Approved :: MIT License
Classifier: Programming Language :: Python :: 2.7
Classifier: Programming Language :: Python :: 3.4
Classifier: Programming Language :: Python :: 3.5
Classifier: Programming Language :: Python :: 3.6
Classifier: Programming Language :: Python :: 3.7
Classifier: Programming Language :: Python :: 3.8
